{"user_no":"230773225288","icon":1054130,"highestscore":[{"arena_id":"59","bestscore":2746728,"member":[{"id":199021,"member_id":1144105,"lv":60,"ex_flg":1,"rankId":13269},{"id":199022,"member_id":1144130,"lv":60,"ex_flg":1,"rankId":13269},{"id":199023,"member_id":1143127,"lv":60,"ex_flg":1,"rankId":13269},{"id":199024,"member_id":1113140,"lv":60,"ex_flg":1,"rankId":13269},{"id":199025,"member_id":1114127,"lv":60,"ex_flg":1,"rankId":13269},{"id":199026,"member_id":1113119,"lv":60,"ex_flg":1,"rankId":13269},{"id":199027,"member_id":1174100,"lv":60,"ex_flg":1,"rankId":13269},{"id":199028,"member_id":1174130,"lv":60,"ex_flg":1,"rankId":13269},{"id":199029,"member_id":1174107,"lv":60,"ex_flg":1,"rankId":13269},{"id":199030,"member_id":1163124,"lv":60,"ex_flg":1,"rankId":13269},{"id":199031,"member_id":1164100,"lv":60,"ex_flg":1,"rankId":13269},{"id":199032,"member_id":1163110,"lv":60,"ex_flg":1,"rankId":13269},{"id":199033,"member_id":1123120,"lv":60,"ex_flg":1,"rankId":13269},{"id":199034,"member_id":1124125,"lv":60,"ex_flg":1,"rankId":13269},{"id":199035,"member_id":1124100,"lv":60,"ex_flg":1,"rankId":13269}],"party":[{"id":66341,"form_no":1,"main":1144105,"sub1":1144130,"sub2":1143127,"weapon":411405,"acc":224165,"specialskill":114002,"rankId":13269},{"id":66342,"form_no":2,"main":1113140,"sub1":1114127,"sub2":1113119,"weapon":411105,"acc":223165,"specialskill":111002,"rankId":13269},{"id":66343,"form_no":3,"main":1174100,"sub1":1174130,"sub2":1174107,"weapon":324306,"acc":224165,"specialskill":117001,"rankId":13269},{"id":66344,"form_no":4,"main":1163124,"sub1":1164100,"sub2":1163110,"weapon":411605,"acc":223165,"specialskill":116001,"rankId":13269},{"id":66345,"form_no":5,"main":1123120,"sub1":1124125,"sub2":1124100,"weapon":411205,"acc":224175,"specialskill":112001,"rankId":13269}]},{"arena_id":"60","bestscore":2674504,"member":[{"id":304396,"member_id":1143112,"lv":60,"ex_flg":1,"rankId":20294},{"id":304397,"member_id":1144105,"lv":60,"ex_flg":1,"rankId":20294},{"id":304398,"member_id":1143100,"lv":60,"ex_flg":1,"rankId":20294},{"id":304399,"member_id":1113119,"lv":60,"ex_flg":1,"rankId":20294},{"id":304400,"member_id":1114127,"lv":60,"ex_flg":1,"rankId":20294},{"id":304401,"member_id":1113140,"lv":60,"ex_flg":1,"rankId":20294},{"id":304402,"member_id":1174107,"lv":60,"ex_flg":1,"rankId":20294},{"id":304403,"member_id":1174130,"lv":60,"ex_flg":1,"rankId":20294},{"id":304404,"member_id":1174100,"lv":60,"ex_flg":1,"rankId":20294},{"id":304405,"member_id":1004119,"lv":60,"ex_flg":1,"rankId":20294},{"id":304406,"member_id":1004141,"lv":60,"ex_flg":1,"rankId":20294},{"id":304407,"member_id":1004116,"lv":60,"ex_flg":1,"rankId":20294},{"id":304408,"member_id":1073100,"lv":60,"ex_flg":1,"rankId":20294},{"id":304409,"member_id":1073124,"lv":60,"ex_flg":1,"rankId":20294},{"id":304410,"member_id":1072100,"lv":60,"ex_flg":1,"rankId":20294}],"party":[{"id":101466,"form_no":1,"main":1143112,"sub1":1144105,"sub2":1143100,"weapon":411405,"acc":224135,"specialskill":114002,"rankId":20294},{"id":101467,"form_no":2,"main":1113119,"sub1":1114127,"sub2":1113140,"weapon":411105,"acc":224135,"specialskill":111002,"rankId":20294},{"id":101468,"form_no":3,"main":1174107,"sub1":1174130,"sub2":1174100,"weapon":324306,"acc":224235,"specialskill":117001,"rankId":20294},{"id":101469,"form_no":4,"main":1004119,"sub1":1004141,"sub2":1004116,"weapon":410005,"acc":223135,"specialskill":100011,"rankId":20294},{"id":101470,"form_no":5,"main":1073100,"sub1":1073124,"sub2":1072100,"weapon":314106,"acc":234135,"specialskill":107001,"rankId":20294}]}]}