{"user_no":"282685175920","icon":1084100,"highestscore":[{"arena_id":"57","bestscore":3559400,"member":[{"id":43111,"member_id":1024132,"lv":60,"ex_flg":1,"rankId":2875},{"id":43112,"member_id":1024137,"lv":60,"ex_flg":1,"rankId":2875},{"id":43113,"member_id":1143100,"lv":60,"ex_flg":1,"rankId":2875},{"id":43114,"member_id":1153143,"lv":60,"ex_flg":1,"rankId":2875},{"id":43115,"member_id":1154117,"lv":60,"ex_flg":1,"rankId":2875},{"id":43116,"member_id":1194117,"lv":60,"ex_flg":1,"rankId":2875},{"id":43117,"member_id":1134100,"lv":60,"ex_flg":1,"rankId":2875},{"id":43118,"member_id":1134117,"lv":60,"ex_flg":1,"rankId":2875},{"id":43119,"member_id":1134110,"lv":60,"ex_flg":1,"rankId":2875},{"id":43120,"member_id":1004141,"lv":60,"ex_flg":1,"rankId":2875},{"id":43121,"member_id":1004116,"lv":60,"ex_flg":1,"rankId":2875},{"id":43122,"member_id":1014142,"lv":60,"ex_flg":1,"rankId":2875},{"id":43123,"member_id":1064107,"lv":60,"ex_flg":1,"rankId":2875},{"id":43124,"member_id":1064100,"lv":60,"ex_flg":1,"rankId":2875},{"id":43125,"member_id":1094126,"lv":60,"ex_flg":1,"rankId":2875}],"party":[{"id":14371,"form_no":1,"main":1024132,"sub1":1024137,"sub2":1143100,"weapon":410205,"acc":224156,"specialskill":102001,"rankId":2875},{"id":14372,"form_no":2,"main":1153143,"sub1":1154117,"sub2":1194117,"weapon":124556,"acc":224144,"specialskill":115011,"rankId":2875},{"id":14373,"form_no":3,"main":1134100,"sub1":1134117,"sub2":1134110,"weapon":411305,"acc":224145,"specialskill":113002,"rankId":2875},{"id":14374,"form_no":4,"main":1004141,"sub1":1004116,"sub2":1014142,"weapon":410005,"acc":224165,"specialskill":100002,"rankId":2875},{"id":14375,"form_no":5,"main":1064107,"sub1":1064100,"sub2":1094126,"weapon":324406,"acc":0,"specialskill":106002,"rankId":2875}]},{"arena_id":"58","bestscore":3569720,"member":[{"id":146476,"member_id":1024132,"lv":60,"ex_flg":1,"rankId":9766},{"id":146477,"member_id":1024100,"lv":60,"ex_flg":1,"rankId":9766},{"id":146478,"member_id":1024126,"lv":60,"ex_flg":1,"rankId":9766},{"id":146479,"member_id":1053127,"lv":60,"ex_flg":1,"rankId":9766},{"id":146480,"member_id":1054100,"lv":60,"ex_flg":1,"rankId":9766},{"id":146481,"member_id":1053139,"lv":60,"ex_flg":1,"rankId":9766},{"id":146482,"member_id":1134117,"lv":60,"ex_flg":1,"rankId":9766},{"id":146483,"member_id":1134110,"lv":60,"ex_flg":1,"rankId":9766},{"id":146484,"member_id":1134100,"lv":60,"ex_flg":1,"rankId":9766},{"id":146485,"member_id":1004141,"lv":60,"ex_flg":1,"rankId":9766},{"id":146486,"member_id":1004127,"lv":60,"ex_flg":1,"rankId":9766},{"id":146487,"member_id":1014142,"lv":60,"ex_flg":1,"rankId":9766},{"id":146488,"member_id":1064100,"lv":60,"ex_flg":1,"rankId":9766},{"id":146489,"member_id":1064107,"lv":60,"ex_flg":1,"rankId":9766},{"id":146490,"member_id":1064118,"lv":60,"ex_flg":1,"rankId":9766}],"party":[{"id":48826,"form_no":1,"main":1024132,"sub1":1024100,"sub2":1024126,"weapon":410205,"acc":223175,"specialskill":102011,"rankId":9766},{"id":48827,"form_no":2,"main":1053127,"sub1":1054100,"sub2":1053139,"weapon":410505,"acc":223175,"specialskill":105002,"rankId":9766},{"id":48828,"form_no":3,"main":1134117,"sub1":1134110,"sub2":1134100,"weapon":324406,"acc":224175,"specialskill":113002,"rankId":9766},{"id":48829,"form_no":4,"main":1004141,"sub1":1004127,"sub2":1014142,"weapon":410005,"acc":0,"specialskill":100002,"rankId":9766},{"id":48830,"form_no":5,"main":1064100,"sub1":1064107,"sub2":1064118,"weapon":410605,"acc":223175,"specialskill":106002,"rankId":9766}]},{"arena_id":"59","bestscore":3451384,"member":[{"id":283036,"member_id":1024132,"lv":60,"ex_flg":1,"rankId":18870},{"id":283037,"member_id":1014142,"lv":60,"ex_flg":1,"rankId":18870},{"id":283038,"member_id":1024126,"lv":60,"ex_flg":1,"rankId":18870},{"id":283039,"member_id":1194125,"lv":60,"ex_flg":1,"rankId":18870},{"id":283040,"member_id":1194100,"lv":60,"ex_flg":1,"rankId":18870},{"id":283041,"member_id":1054113,"lv":60,"ex_flg":1,"rankId":18870},{"id":283042,"member_id":1104100,"lv":60,"ex_flg":1,"rankId":18870},{"id":283043,"member_id":1104127,"lv":60,"ex_flg":1,"rankId":18870},{"id":283044,"member_id":1104110,"lv":60,"ex_flg":1,"rankId":18870},{"id":283045,"member_id":1004141,"lv":60,"ex_flg":1,"rankId":18870},{"id":283046,"member_id":1004127,"lv":60,"ex_flg":1,"rankId":18870},{"id":283047,"member_id":1004116,"lv":60,"ex_flg":1,"rankId":18870},{"id":283048,"member_id":1133128,"lv":60,"ex_flg":1,"rankId":18870},{"id":283049,"member_id":1134110,"lv":60,"ex_flg":1,"rankId":18870},{"id":283050,"member_id":1024113,"lv":60,"ex_flg":1,"rankId":18870}],"party":[{"id":94346,"form_no":1,"main":1024132,"sub1":1014142,"sub2":1024126,"weapon":410205,"acc":224235,"specialskill":102001,"rankId":18870},{"id":94347,"form_no":2,"main":1194125,"sub1":1194100,"sub2":1054113,"weapon":124576,"acc":224165,"specialskill":119001,"rankId":18870},{"id":94348,"form_no":3,"main":1104100,"sub1":1104127,"sub2":1104110,"weapon":411005,"acc":234145,"specialskill":110002,"rankId":18870},{"id":94349,"form_no":4,"main":1004141,"sub1":1004127,"sub2":1004116,"weapon":410005,"acc":224164,"specialskill":100011,"rankId":18870},{"id":94350,"form_no":5,"main":1133128,"sub1":1134110,"sub2":1024113,"weapon":324406,"acc":224175,"specialskill":113011,"rankId":18870}]},{"arena_id":"60","bestscore":2966928,"member":[{"id":337351,"member_id":1113119,"lv":60,"ex_flg":1,"rankId":22491},{"id":337352,"member_id":1113140,"lv":60,"ex_flg":1,"rankId":22491},{"id":337353,"member_id":1014142,"lv":60,"ex_flg":1,"rankId":22491},{"id":337354,"member_id":1024137,"lv":60,"ex_flg":1,"rankId":22491},{"id":337355,"member_id":1143100,"lv":60,"ex_flg":1,"rankId":22491},{"id":337356,"member_id":1183130,"lv":60,"ex_flg":1,"rankId":22491},{"id":337357,"member_id":1174107,"lv":60,"ex_flg":1,"rankId":22491},{"id":337358,"member_id":1174123,"lv":60,"ex_flg":1,"rankId":22491},{"id":337359,"member_id":1174130,"lv":60,"ex_flg":1,"rankId":22491},{"id":337360,"member_id":1074119,"lv":60,"ex_flg":1,"rankId":22491},{"id":337361,"member_id":1074129,"lv":60,"ex_flg":1,"rankId":22491},{"id":337362,"member_id":1074139,"lv":60,"ex_flg":1,"rankId":22491},{"id":337363,"member_id":1004119,"lv":60,"ex_flg":1,"rankId":22491},{"id":337364,"member_id":1004141,"lv":60,"ex_flg":1,"rankId":22491},{"id":337365,"member_id":1004116,"lv":60,"ex_flg":1,"rankId":22491}],"party":[{"id":112451,"form_no":1,"main":1113119,"sub1":1113140,"sub2":1014142,"weapon":324105,"acc":224235,"specialskill":111002,"rankId":22491},{"id":112452,"form_no":2,"main":1024137,"sub1":1143100,"sub2":1183130,"weapon":410205,"acc":224235,"specialskill":102001,"rankId":22491},{"id":112453,"form_no":3,"main":1174107,"sub1":1174123,"sub2":1174130,"weapon":314306,"acc":224175,"specialskill":117001,"rankId":22491},{"id":112454,"form_no":4,"main":1074119,"sub1":1074129,"sub2":1074139,"weapon":410705,"acc":224156,"specialskill":107002,"rankId":22491},{"id":112455,"form_no":5,"main":1004119,"sub1":1004141,"sub2":1004116,"weapon":410005,"acc":224165,"specialskill":100011,"rankId":22491}]}]}