{"user_no":"346729914163","icon":1104100,"highestscore":[{"arena_id":"59","bestscore":2819920,"member":[{"id":211261,"member_id":1024113,"lv":60,"ex_flg":1,"rankId":14085},{"id":211262,"member_id":1024126,"lv":60,"ex_flg":1,"rankId":14085},{"id":211263,"member_id":1024100,"lv":60,"ex_flg":1,"rankId":14085},{"id":211264,"member_id":1194125,"lv":60,"ex_flg":1,"rankId":14085},{"id":211265,"member_id":1194100,"lv":60,"ex_flg":1,"rankId":14085},{"id":211266,"member_id":1094100,"lv":60,"ex_flg":1,"rankId":14085},{"id":211267,"member_id":1104100,"lv":60,"ex_flg":1,"rankId":14085},{"id":211268,"member_id":1104116,"lv":60,"ex_flg":1,"rankId":14085},{"id":211269,"member_id":1104127,"lv":60,"ex_flg":1,"rankId":14085},{"id":211270,"member_id":1054113,"lv":60,"ex_flg":1,"rankId":14085},{"id":211271,"member_id":1054123,"lv":60,"ex_flg":1,"rankId":14085},{"id":211272,"member_id":1054100,"lv":60,"ex_flg":1,"rankId":14085},{"id":211273,"member_id":1174100,"lv":60,"ex_flg":1,"rankId":14085},{"id":211274,"member_id":1174130,"lv":60,"ex_flg":1,"rankId":14085},{"id":211275,"member_id":1004116,"lv":60,"ex_flg":1,"rankId":14085}],"party":[{"id":70421,"form_no":1,"main":1024113,"sub1":1024126,"sub2":1024100,"weapon":314406,"acc":234145,"specialskill":102011,"rankId":14085},{"id":70422,"form_no":2,"main":1194125,"sub1":1194100,"sub2":1094100,"weapon":314506,"acc":234145,"specialskill":119001,"rankId":14085},{"id":70423,"form_no":3,"main":1104100,"sub1":1104116,"sub2":1104127,"weapon":411005,"acc":234145,"specialskill":110002,"rankId":14085},{"id":70424,"form_no":4,"main":1054113,"sub1":1054123,"sub2":1054100,"weapon":324406,"acc":234136,"specialskill":105002,"rankId":14085},{"id":70425,"form_no":5,"main":1174100,"sub1":1174130,"sub2":1004116,"weapon":314305,"acc":234136,"specialskill":117001,"rankId":14085}]}]}