{"user_no":"422934004050","icon":1034142,"highestscore":[{"arena_id":"57","bestscore":3321480,"member":[{"id":52411,"member_id":1004141,"lv":60,"ex_flg":1,"rankId":3495},{"id":52412,"member_id":1004116,"lv":60,"ex_flg":1,"rankId":3495},{"id":52413,"member_id":1014142,"lv":60,"ex_flg":1,"rankId":3495},{"id":52414,"member_id":1153143,"lv":60,"ex_flg":1,"rankId":3495},{"id":52415,"member_id":1154117,"lv":60,"ex_flg":1,"rankId":3495},{"id":52416,"member_id":1154105,"lv":60,"ex_flg":1,"rankId":3495},{"id":52417,"member_id":1133115,"lv":60,"ex_flg":1,"rankId":3495},{"id":52418,"member_id":1134100,"lv":60,"ex_flg":1,"rankId":3495},{"id":52419,"member_id":1134117,"lv":60,"ex_flg":1,"rankId":3495},{"id":52420,"member_id":1102102,"lv":60,"ex_flg":1,"rankId":3495},{"id":52421,"member_id":1104116,"lv":60,"ex_flg":1,"rankId":3495},{"id":52422,"member_id":1103107,"lv":60,"ex_flg":1,"rankId":3495},{"id":52423,"member_id":1094126,"lv":60,"ex_flg":1,"rankId":3495},{"id":52424,"member_id":1094100,"lv":60,"ex_flg":1,"rankId":3495},{"id":52425,"member_id":1093130,"lv":60,"ex_flg":1,"rankId":3495}],"party":[{"id":17471,"form_no":1,"main":1004141,"sub1":1004116,"sub2":1014142,"weapon":324106,"acc":224156,"specialskill":100002,"rankId":3495},{"id":17472,"form_no":2,"main":1153143,"sub1":1154117,"sub2":1154105,"weapon":124556,"acc":224156,"specialskill":115011,"rankId":3495},{"id":17473,"form_no":3,"main":1133115,"sub1":1134100,"sub2":1134117,"weapon":411305,"acc":224145,"specialskill":113002,"rankId":3495},{"id":17474,"form_no":4,"main":1102102,"sub1":1104116,"sub2":1103107,"weapon":324406,"acc":234125,"specialskill":110001,"rankId":3495},{"id":17475,"form_no":5,"main":1094126,"sub1":1094100,"sub2":1093130,"weapon":124556,"acc":234125,"specialskill":109002,"rankId":3495}]},{"arena_id":"58","bestscore":3276848,"member":[{"id":124756,"member_id":1023107,"lv":60,"ex_flg":1,"rankId":8318},{"id":124757,"member_id":1024141,"lv":60,"ex_flg":1,"rankId":8318},{"id":124758,"member_id":1023104,"lv":60,"ex_flg":1,"rankId":8318},{"id":124759,"member_id":1053127,"lv":60,"ex_flg":1,"rankId":8318},{"id":124760,"member_id":1053139,"lv":60,"ex_flg":1,"rankId":8318},{"id":124761,"member_id":1054100,"lv":60,"ex_flg":1,"rankId":8318},{"id":124762,"member_id":1134117,"lv":60,"ex_flg":1,"rankId":8318},{"id":124763,"member_id":1134110,"lv":60,"ex_flg":1,"rankId":8318},{"id":124764,"member_id":1134123,"lv":60,"ex_flg":1,"rankId":8318},{"id":124765,"member_id":1004141,"lv":60,"ex_flg":1,"rankId":8318},{"id":124766,"member_id":1004116,"lv":60,"ex_flg":1,"rankId":8318},{"id":124767,"member_id":1003137,"lv":60,"ex_flg":1,"rankId":8318},{"id":124768,"member_id":1063116,"lv":60,"ex_flg":1,"rankId":8318},{"id":124769,"member_id":1064118,"lv":60,"ex_flg":1,"rankId":8318},{"id":124770,"member_id":1064100,"lv":60,"ex_flg":1,"rankId":8318}],"party":[{"id":41586,"form_no":1,"main":1023107,"sub1":1024141,"sub2":1023104,"weapon":314406,"acc":234136,"specialskill":102001,"rankId":8318},{"id":41587,"form_no":2,"main":1053127,"sub1":1053139,"sub2":1054100,"weapon":410505,"acc":234136,"specialskill":105002,"rankId":8318},{"id":41588,"form_no":3,"main":1134117,"sub1":1134110,"sub2":1134123,"weapon":324406,"acc":234136,"specialskill":113002,"rankId":8318},{"id":41589,"form_no":4,"main":1004141,"sub1":1004116,"sub2":1003137,"weapon":324106,"acc":224175,"specialskill":100001,"rankId":8318},{"id":41590,"form_no":5,"main":1063116,"sub1":1064118,"sub2":1064100,"weapon":410605,"acc":224156,"specialskill":106002,"rankId":8318}]},{"arena_id":"59","bestscore":3227048,"member":[{"id":293206,"member_id":1024113,"lv":60,"ex_flg":1,"rankId":19548},{"id":293207,"member_id":1024141,"lv":60,"ex_flg":1,"rankId":19548},{"id":293208,"member_id":1024137,"lv":60,"ex_flg":1,"rankId":19548},{"id":293209,"member_id":1194125,"lv":60,"ex_flg":1,"rankId":19548},{"id":293210,"member_id":1054113,"lv":60,"ex_flg":1,"rankId":19548},{"id":293211,"member_id":1194100,"lv":60,"ex_flg":1,"rankId":19548},{"id":293212,"member_id":1104100,"lv":60,"ex_flg":1,"rankId":19548},{"id":293213,"member_id":1104116,"lv":60,"ex_flg":1,"rankId":19548},{"id":293214,"member_id":1104127,"lv":60,"ex_flg":1,"rankId":19548},{"id":293215,"member_id":1004141,"lv":60,"ex_flg":1,"rankId":19548},{"id":293216,"member_id":1004116,"lv":60,"ex_flg":1,"rankId":19548},{"id":293217,"member_id":1014142,"lv":60,"ex_flg":1,"rankId":19548},{"id":293218,"member_id":1133128,"lv":60,"ex_flg":1,"rankId":19548},{"id":293219,"member_id":1134110,"lv":60,"ex_flg":1,"rankId":19548},{"id":293220,"member_id":1134117,"lv":60,"ex_flg":1,"rankId":19548}],"party":[{"id":97736,"form_no":1,"main":1024113,"sub1":1024141,"sub2":1024137,"weapon":324406,"acc":233145,"specialskill":102001,"rankId":19548},{"id":97737,"form_no":2,"main":1194125,"sub1":1054113,"sub2":1194100,"weapon":124576,"acc":234146,"specialskill":119001,"rankId":19548},{"id":97738,"form_no":3,"main":1104100,"sub1":1104116,"sub2":1104127,"weapon":124476,"acc":234145,"specialskill":110002,"rankId":19548},{"id":97739,"form_no":4,"main":1004141,"sub1":1004116,"sub2":1014142,"weapon":410005,"acc":233146,"specialskill":100011,"rankId":19548},{"id":97740,"form_no":5,"main":1133128,"sub1":1134110,"sub2":1134117,"weapon":314406,"acc":234145,"specialskill":113011,"rankId":19548}]},{"arena_id":"60","bestscore":3206232,"member":[{"id":356401,"member_id":1114114,"lv":60,"ex_flg":1,"rankId":23761},{"id":356402,"member_id":1113140,"lv":60,"ex_flg":1,"rankId":23761},{"id":356403,"member_id":1114127,"lv":60,"ex_flg":1,"rankId":23761},{"id":356404,"member_id":1024137,"lv":60,"ex_flg":1,"rankId":23761},{"id":356405,"member_id":1024100,"lv":60,"ex_flg":1,"rankId":23761},{"id":356406,"member_id":1014142,"lv":60,"ex_flg":1,"rankId":23761},{"id":356407,"member_id":1074119,"lv":60,"ex_flg":1,"rankId":23761},{"id":356408,"member_id":1074100,"lv":60,"ex_flg":1,"rankId":23761},{"id":356409,"member_id":1073100,"lv":60,"ex_flg":1,"rankId":23761},{"id":356410,"member_id":1174107,"lv":60,"ex_flg":1,"rankId":23761},{"id":356411,"member_id":1174100,"lv":60,"ex_flg":1,"rankId":23761},{"id":356412,"member_id":1034142,"lv":60,"ex_flg":1,"rankId":23761},{"id":356413,"member_id":1004119,"lv":60,"ex_flg":1,"rankId":23761},{"id":356414,"member_id":1004116,"lv":60,"ex_flg":1,"rankId":23761},{"id":356415,"member_id":1004141,"lv":60,"ex_flg":1,"rankId":23761}],"party":[{"id":118801,"form_no":1,"main":1114114,"sub1":1113140,"sub2":1114127,"weapon":411105,"acc":234136,"specialskill":111002,"rankId":23761},{"id":118802,"form_no":2,"main":1024137,"sub1":1024100,"sub2":1014142,"weapon":410205,"acc":234146,"specialskill":102001,"rankId":23761},{"id":118803,"form_no":3,"main":1074119,"sub1":1074100,"sub2":1073100,"weapon":324106,"acc":224135,"specialskill":107002,"rankId":23761},{"id":118804,"form_no":4,"main":1174107,"sub1":1174100,"sub2":1034142,"weapon":324306,"acc":224136,"specialskill":117001,"rankId":23761},{"id":118805,"form_no":5,"main":1004119,"sub1":1004116,"sub2":1004141,"weapon":410005,"acc":234136,"specialskill":100011,"rankId":23761}]}]}