{"user_no":"542018301797","icon":1023123,"highestscore":[{"arena_id":"57","bestscore":3524704,"member":[{"id":57106,"member_id":1024132,"lv":60,"ex_flg":1,"rankId":3808},{"id":57107,"member_id":1024126,"lv":60,"ex_flg":1,"rankId":3808},{"id":57108,"member_id":1014142,"lv":60,"ex_flg":1,"rankId":3808},{"id":57109,"member_id":1153143,"lv":60,"ex_flg":1,"rankId":3808},{"id":57110,"member_id":1154113,"lv":60,"ex_flg":1,"rankId":3808},{"id":57111,"member_id":1154117,"lv":60,"ex_flg":1,"rankId":3808},{"id":57112,"member_id":1134100,"lv":60,"ex_flg":1,"rankId":3808},{"id":57113,"member_id":1134123,"lv":60,"ex_flg":1,"rankId":3808},{"id":57114,"member_id":1134110,"lv":60,"ex_flg":1,"rankId":3808},{"id":57115,"member_id":1004141,"lv":60,"ex_flg":1,"rankId":3808},{"id":57116,"member_id":1004116,"lv":60,"ex_flg":1,"rankId":3808},{"id":57117,"member_id":1003137,"lv":60,"ex_flg":1,"rankId":3808},{"id":57118,"member_id":1102102,"lv":60,"ex_flg":1,"rankId":3808},{"id":57119,"member_id":1103107,"lv":60,"ex_flg":1,"rankId":3808},{"id":57120,"member_id":1104127,"lv":60,"ex_flg":1,"rankId":3808}],"party":[{"id":19036,"form_no":1,"main":1024132,"sub1":1024126,"sub2":1014142,"weapon":410205,"acc":223145,"specialskill":102001,"rankId":3808},{"id":19037,"form_no":2,"main":1153143,"sub1":1154113,"sub2":1154117,"weapon":124556,"acc":224145,"specialskill":115011,"rankId":3808},{"id":19038,"form_no":3,"main":1134100,"sub1":1134123,"sub2":1134110,"weapon":411305,"acc":224145,"specialskill":113002,"rankId":3808},{"id":19039,"form_no":4,"main":1004141,"sub1":1004116,"sub2":1003137,"weapon":324106,"acc":223145,"specialskill":100002,"rankId":3808},{"id":19040,"form_no":5,"main":1102102,"sub1":1103107,"sub2":1104127,"weapon":324405,"acc":223145,"specialskill":110002,"rankId":3808}]},{"arena_id":"58","bestscore":3347368,"member":[{"id":154411,"member_id":1024132,"lv":60,"ex_flg":1,"rankId":10295},{"id":154412,"member_id":1024126,"lv":60,"ex_flg":1,"rankId":10295},{"id":154413,"member_id":1024141,"lv":60,"ex_flg":1,"rankId":10295},{"id":154414,"member_id":1053127,"lv":60,"ex_flg":1,"rankId":10295},{"id":154415,"member_id":1054123,"lv":60,"ex_flg":1,"rankId":10295},{"id":154416,"member_id":1053139,"lv":60,"ex_flg":1,"rankId":10295},{"id":154417,"member_id":1134117,"lv":60,"ex_flg":1,"rankId":10295},{"id":154418,"member_id":1134110,"lv":60,"ex_flg":1,"rankId":10295},{"id":154419,"member_id":1134100,"lv":60,"ex_flg":1,"rankId":10295},{"id":154420,"member_id":1004141,"lv":60,"ex_flg":1,"rankId":10295},{"id":154421,"member_id":1004116,"lv":60,"ex_flg":1,"rankId":10295},{"id":154422,"member_id":1014142,"lv":60,"ex_flg":1,"rankId":10295},{"id":154423,"member_id":1064100,"lv":60,"ex_flg":1,"rankId":10295},{"id":154424,"member_id":1064118,"lv":60,"ex_flg":1,"rankId":10295},{"id":154425,"member_id":1064129,"lv":60,"ex_flg":1,"rankId":10295}],"party":[{"id":51471,"form_no":1,"main":1024132,"sub1":1024126,"sub2":1024141,"weapon":410205,"acc":223275,"specialskill":102001,"rankId":10295},{"id":51472,"form_no":2,"main":1053127,"sub1":1054123,"sub2":1053139,"weapon":410505,"acc":223175,"specialskill":105002,"rankId":10295},{"id":51473,"form_no":3,"main":1134117,"sub1":1134110,"sub2":1134100,"weapon":411305,"acc":224175,"specialskill":113002,"rankId":10295},{"id":51474,"form_no":4,"main":1004141,"sub1":1004116,"sub2":1014142,"weapon":324106,"acc":223175,"specialskill":100002,"rankId":10295},{"id":51475,"form_no":5,"main":1064100,"sub1":1064118,"sub2":1064129,"weapon":324405,"acc":223175,"specialskill":106002,"rankId":10295}]},{"arena_id":"59","bestscore":3367416,"member":[{"id":267106,"member_id":1023123,"lv":60,"ex_flg":1,"rankId":17808},{"id":267107,"member_id":1024126,"lv":60,"ex_flg":1,"rankId":17808},{"id":267108,"member_id":1024141,"lv":60,"ex_flg":1,"rankId":17808},{"id":267109,"member_id":1194125,"lv":60,"ex_flg":1,"rankId":17808},{"id":267110,"member_id":1194100,"lv":60,"ex_flg":1,"rankId":17808},{"id":267111,"member_id":1054113,"lv":60,"ex_flg":1,"rankId":17808},{"id":267112,"member_id":1104100,"lv":60,"ex_flg":1,"rankId":17808},{"id":267113,"member_id":1104116,"lv":60,"ex_flg":1,"rankId":17808},{"id":267114,"member_id":1103134,"lv":60,"ex_flg":1,"rankId":17808},{"id":267115,"member_id":1004141,"lv":60,"ex_flg":1,"rankId":17808},{"id":267116,"member_id":1004116,"lv":60,"ex_flg":1,"rankId":17808},{"id":267117,"member_id":1014142,"lv":60,"ex_flg":1,"rankId":17808},{"id":267118,"member_id":1133128,"lv":60,"ex_flg":1,"rankId":17808},{"id":267119,"member_id":1134110,"lv":60,"ex_flg":1,"rankId":17808},{"id":267120,"member_id":1054123,"lv":60,"ex_flg":1,"rankId":17808}],"party":[{"id":89036,"form_no":1,"main":1023123,"sub1":1024126,"sub2":1024141,"weapon":410205,"acc":223265,"specialskill":102001,"rankId":17808},{"id":89037,"form_no":2,"main":1194125,"sub1":1194100,"sub2":1054113,"weapon":124576,"acc":234146,"specialskill":119001,"rankId":17808},{"id":89038,"form_no":3,"main":1104100,"sub1":1104116,"sub2":1103134,"weapon":411005,"acc":224165,"specialskill":110002,"rankId":17808},{"id":89039,"form_no":4,"main":1004141,"sub1":1004116,"sub2":1014142,"weapon":324106,"acc":233142,"specialskill":100011,"rankId":17808},{"id":89040,"form_no":5,"main":1133128,"sub1":1134110,"sub2":1054123,"weapon":324405,"acc":224165,"specialskill":113011,"rankId":17808}]},{"arena_id":"60","bestscore":3050696,"member":[{"id":353326,"member_id":1143112,"lv":60,"ex_flg":1,"rankId":23556},{"id":353327,"member_id":1143100,"lv":60,"ex_flg":1,"rankId":23556},{"id":353328,"member_id":1143143,"lv":60,"ex_flg":1,"rankId":23556},{"id":353329,"member_id":1113119,"lv":60,"ex_flg":1,"rankId":23556},{"id":353330,"member_id":1113140,"lv":60,"ex_flg":1,"rankId":23556},{"id":353331,"member_id":1114127,"lv":60,"ex_flg":1,"rankId":23556},{"id":353332,"member_id":1174107,"lv":60,"ex_flg":1,"rankId":23556},{"id":353333,"member_id":1174130,"lv":60,"ex_flg":1,"rankId":23556},{"id":353334,"member_id":1174123,"lv":60,"ex_flg":1,"rankId":23556},{"id":353335,"member_id":1074119,"lv":60,"ex_flg":1,"rankId":23556},{"id":353336,"member_id":1074129,"lv":60,"ex_flg":1,"rankId":23556},{"id":353337,"member_id":1074139,"lv":60,"ex_flg":1,"rankId":23556},{"id":353338,"member_id":1014137,"lv":60,"ex_flg":1,"rankId":23556},{"id":353339,"member_id":1013120,"lv":60,"ex_flg":1,"rankId":23556},{"id":353340,"member_id":1014142,"lv":60,"ex_flg":1,"rankId":23556}],"party":[{"id":117776,"form_no":1,"main":1143112,"sub1":1143100,"sub2":1143143,"weapon":334205,"acc":0,"specialskill":114002,"rankId":23556},{"id":117777,"form_no":2,"main":1113119,"sub1":1113140,"sub2":1114127,"weapon":324106,"acc":224135,"specialskill":111002,"rankId":23556},{"id":117778,"form_no":3,"main":1174107,"sub1":1174130,"sub2":1174123,"weapon":314305,"acc":224235,"specialskill":117001,"rankId":23556},{"id":117779,"form_no":4,"main":1074119,"sub1":1074129,"sub2":1074139,"weapon":410705,"acc":223135,"specialskill":107011,"rankId":23556},{"id":117780,"form_no":5,"main":1014137,"sub1":1013120,"sub2":1014142,"weapon":410105,"acc":223135,"specialskill":101002,"rankId":23556}]}]}