{"user_no":"588115611199","icon":1014142,"highestscore":[{"arena_id":"60","bestscore":2806776,"member":[{"id":308416,"member_id":1074119,"lv":60,"ex_flg":1,"rankId":20562},{"id":308417,"member_id":1074100,"lv":60,"ex_flg":1,"rankId":20562},{"id":308418,"member_id":1073100,"lv":60,"ex_flg":1,"rankId":20562},{"id":308419,"member_id":1113119,"lv":60,"ex_flg":1,"rankId":20562},{"id":308420,"member_id":1114114,"lv":60,"ex_flg":1,"rankId":20562},{"id":308421,"member_id":1114110,"lv":60,"ex_flg":1,"rankId":20562},{"id":308422,"member_id":1174107,"lv":60,"ex_flg":1,"rankId":20562},{"id":308423,"member_id":1004119,"lv":60,"ex_flg":1,"rankId":20562},{"id":308424,"member_id":1164130,"lv":60,"ex_flg":1,"rankId":20562},{"id":308425,"member_id":1014137,"lv":60,"ex_flg":1,"rankId":20562},{"id":308426,"member_id":1014132,"lv":60,"ex_flg":1,"rankId":20562},{"id":308427,"member_id":1014142,"lv":60,"ex_flg":1,"rankId":20562},{"id":308428,"member_id":1063140,"lv":60,"ex_flg":1,"rankId":20562},{"id":308429,"member_id":1133100,"lv":60,"ex_flg":1,"rankId":20562},{"id":308430,"member_id":1062102,"lv":60,"ex_flg":1,"rankId":20562}],"party":[{"id":102806,"form_no":1,"main":1074119,"sub1":1074100,"sub2":1073100,"weapon":324106,"acc":234136,"specialskill":107002,"rankId":20562},{"id":102807,"form_no":2,"main":1113119,"sub1":1114114,"sub2":1114110,"weapon":314106,"acc":234135,"specialskill":111002,"rankId":20562},{"id":102808,"form_no":3,"main":1174107,"sub1":1004119,"sub2":1164130,"weapon":324306,"acc":224145,"specialskill":117001,"rankId":20562},{"id":102809,"form_no":4,"main":1014137,"sub1":1014132,"sub2":1014142,"weapon":410105,"acc":224125,"specialskill":101001,"rankId":20562},{"id":102810,"form_no":5,"main":1063140,"sub1":1133100,"sub2":1062102,"weapon":314405,"acc":224165,"specialskill":106001,"rankId":20562}]}]}