{"user_no":"649532034977","icon":1134123,"highestscore":[{"arena_id":"57","bestscore":3559432,"member":[{"id":14146,"member_id":1004141,"lv":60,"ex_flg":1,"rankId":944},{"id":14147,"member_id":1004116,"lv":60,"ex_flg":1,"rankId":944},{"id":14148,"member_id":1004127,"lv":60,"ex_flg":1,"rankId":944},{"id":14149,"member_id":1024126,"lv":60,"ex_flg":1,"rankId":944},{"id":14150,"member_id":1143100,"lv":60,"ex_flg":1,"rankId":944},{"id":14151,"member_id":1024100,"lv":60,"ex_flg":1,"rankId":944},{"id":14152,"member_id":1134100,"lv":60,"ex_flg":1,"rankId":944},{"id":14153,"member_id":1134110,"lv":60,"ex_flg":1,"rankId":944},{"id":14154,"member_id":1014132,"lv":60,"ex_flg":1,"rankId":944},{"id":14155,"member_id":1064107,"lv":60,"ex_flg":1,"rankId":944},{"id":14156,"member_id":1064100,"lv":60,"ex_flg":1,"rankId":944},{"id":14157,"member_id":1134117,"lv":60,"ex_flg":1,"rankId":944},{"id":14158,"member_id":1054130,"lv":60,"ex_flg":1,"rankId":944},{"id":14159,"member_id":1054123,"lv":60,"ex_flg":1,"rankId":944},{"id":14160,"member_id":1053139,"lv":60,"ex_flg":1,"rankId":944}],"party":[{"id":4716,"form_no":1,"main":1004141,"sub1":1004116,"sub2":1004127,"weapon":324106,"acc":234124,"specialskill":100002,"rankId":944},{"id":4717,"form_no":2,"main":1024126,"sub1":1143100,"sub2":1024100,"weapon":410205,"acc":224145,"specialskill":102002,"rankId":944},{"id":4718,"form_no":3,"main":1134100,"sub1":1134110,"sub2":1014132,"weapon":411305,"acc":224145,"specialskill":113002,"rankId":944},{"id":4719,"form_no":4,"main":1064107,"sub1":1064100,"sub2":1134117,"weapon":324406,"acc":224145,"specialskill":106002,"rankId":944},{"id":4720,"form_no":5,"main":1054130,"sub1":1054123,"sub2":1053139,"weapon":410505,"acc":224145,"specialskill":105002,"rankId":944}]},{"arena_id":"58","bestscore":3750936,"member":[{"id":178171,"member_id":1024132,"lv":60,"ex_flg":1,"rankId":11879},{"id":178172,"member_id":1024126,"lv":60,"ex_flg":1,"rankId":11879},{"id":178173,"member_id":1024141,"lv":60,"ex_flg":1,"rankId":11879},{"id":178174,"member_id":1134117,"lv":60,"ex_flg":1,"rankId":11879},{"id":178175,"member_id":1134110,"lv":60,"ex_flg":1,"rankId":11879},{"id":178176,"member_id":1064107,"lv":60,"ex_flg":1,"rankId":11879},{"id":178177,"member_id":1053127,"lv":60,"ex_flg":1,"rankId":11879},{"id":178178,"member_id":1054123,"lv":60,"ex_flg":1,"rankId":11879},{"id":178179,"member_id":1053139,"lv":60,"ex_flg":1,"rankId":11879},{"id":178180,"member_id":1004141,"lv":60,"ex_flg":1,"rankId":11879},{"id":178181,"member_id":1014142,"lv":60,"ex_flg":1,"rankId":11879},{"id":178182,"member_id":1004127,"lv":60,"ex_flg":1,"rankId":11879},{"id":178183,"member_id":1064100,"lv":60,"ex_flg":1,"rankId":11879},{"id":178184,"member_id":1064129,"lv":60,"ex_flg":1,"rankId":11879},{"id":178185,"member_id":1064118,"lv":60,"ex_flg":1,"rankId":11879}],"party":[{"id":59391,"form_no":1,"main":1024132,"sub1":1024126,"sub2":1024141,"weapon":410205,"acc":223175,"specialskill":102001,"rankId":11879},{"id":59392,"form_no":2,"main":1134117,"sub1":1134110,"sub2":1064107,"weapon":324406,"acc":224175,"specialskill":113002,"rankId":11879},{"id":59393,"form_no":3,"main":1053127,"sub1":1054123,"sub2":1053139,"weapon":410505,"acc":223176,"specialskill":105002,"rankId":11879},{"id":59394,"form_no":4,"main":1004141,"sub1":1014142,"sub2":1004127,"weapon":324106,"acc":223150,"specialskill":100002,"rankId":11879},{"id":59395,"form_no":5,"main":1064100,"sub1":1064129,"sub2":1064118,"weapon":410605,"acc":223175,"specialskill":106002,"rankId":11879}]},{"arena_id":"59","bestscore":3263880,"member":[{"id":294226,"member_id":1024132,"lv":60,"ex_flg":1,"rankId":19616},{"id":294227,"member_id":1113140,"lv":60,"ex_flg":1,"rankId":19616},{"id":294228,"member_id":1143100,"lv":60,"ex_flg":1,"rankId":19616},{"id":294229,"member_id":1104100,"lv":60,"ex_flg":1,"rankId":19616},{"id":294230,"member_id":1104116,"lv":60,"ex_flg":1,"rankId":19616},{"id":294231,"member_id":1104127,"lv":60,"ex_flg":1,"rankId":19616},{"id":294232,"member_id":1194125,"lv":60,"ex_flg":1,"rankId":19616},{"id":294233,"member_id":1194100,"lv":60,"ex_flg":1,"rankId":19616},{"id":294234,"member_id":1054113,"lv":60,"ex_flg":1,"rankId":19616},{"id":294235,"member_id":1004141,"lv":60,"ex_flg":1,"rankId":19616},{"id":294236,"member_id":1014142,"lv":60,"ex_flg":1,"rankId":19616},{"id":294237,"member_id":1004127,"lv":60,"ex_flg":1,"rankId":19616},{"id":294238,"member_id":1133128,"lv":60,"ex_flg":1,"rankId":19616},{"id":294239,"member_id":1134117,"lv":60,"ex_flg":1,"rankId":19616},{"id":294240,"member_id":1134110,"lv":60,"ex_flg":1,"rankId":19616}],"party":[{"id":98076,"form_no":1,"main":1024132,"sub1":1113140,"sub2":1143100,"weapon":410205,"acc":223265,"specialskill":102001,"rankId":19616},{"id":98077,"form_no":2,"main":1104100,"sub1":1104116,"sub2":1104127,"weapon":324406,"acc":224165,"specialskill":110002,"rankId":19616},{"id":98078,"form_no":3,"main":1194125,"sub1":1194100,"sub2":1054113,"weapon":124576,"acc":224165,"specialskill":119001,"rankId":19616},{"id":98079,"form_no":4,"main":1004141,"sub1":1014142,"sub2":1004127,"weapon":324106,"acc":234145,"specialskill":100002,"rankId":19616},{"id":98080,"form_no":5,"main":1133128,"sub1":1134117,"sub2":1134110,"weapon":314406,"acc":223265,"specialskill":113011,"rankId":19616}]},{"arena_id":"60","bestscore":3540296,"member":[{"id":374341,"member_id":1113119,"lv":60,"ex_flg":1,"rankId":24957},{"id":374342,"member_id":1113140,"lv":60,"ex_flg":1,"rankId":24957},{"id":374343,"member_id":1014142,"lv":60,"ex_flg":1,"rankId":24957},{"id":374344,"member_id":1174107,"lv":60,"ex_flg":1,"rankId":24957},{"id":374345,"member_id":1174130,"lv":60,"ex_flg":1,"rankId":24957},{"id":374346,"member_id":1034142,"lv":60,"ex_flg":1,"rankId":24957},{"id":374347,"member_id":1024137,"lv":60,"ex_flg":1,"rankId":24957},{"id":374348,"member_id":1183130,"lv":60,"ex_flg":1,"rankId":24957},{"id":374349,"member_id":1143100,"lv":60,"ex_flg":1,"rankId":24957},{"id":374350,"member_id":1074119,"lv":60,"ex_flg":1,"rankId":24957},{"id":374351,"member_id":1074139,"lv":60,"ex_flg":1,"rankId":24957},{"id":374352,"member_id":1074129,"lv":60,"ex_flg":1,"rankId":24957},{"id":374353,"member_id":1184100,"lv":60,"ex_flg":1,"rankId":24957},{"id":374354,"member_id":1184117,"lv":60,"ex_flg":1,"rankId":24957},{"id":374355,"member_id":1184127,"lv":60,"ex_flg":1,"rankId":24957}],"party":[{"id":124781,"form_no":1,"main":1113119,"sub1":1113140,"sub2":1014142,"weapon":411105,"acc":224135,"specialskill":111002,"rankId":24957},{"id":124782,"form_no":2,"main":1174107,"sub1":1174130,"sub2":1034142,"weapon":324306,"acc":224135,"specialskill":117001,"rankId":24957},{"id":124783,"form_no":3,"main":1024137,"sub1":1183130,"sub2":1143100,"weapon":410205,"acc":224135,"specialskill":102001,"rankId":24957},{"id":124784,"form_no":4,"main":1074119,"sub1":1074139,"sub2":1074129,"weapon":324106,"acc":224235,"specialskill":107002,"rankId":24957},{"id":124785,"form_no":5,"main":1184100,"sub1":1184117,"sub2":1184127,"weapon":124246,"acc":224135,"specialskill":118001,"rankId":24957}]}]}