{"user_no":"681833205426","icon":1153112,"highestscore":[{"arena_id":"59","bestscore":2946104,"member":[{"id":216136,"member_id":1024132,"lv":60,"ex_flg":1,"rankId":14410},{"id":216137,"member_id":1143100,"lv":60,"ex_flg":1,"rankId":14410},{"id":216138,"member_id":1024126,"lv":60,"ex_flg":1,"rankId":14410},{"id":216139,"member_id":1104100,"lv":60,"ex_flg":1,"rankId":14410},{"id":216140,"member_id":1104116,"lv":60,"ex_flg":1,"rankId":14410},{"id":216141,"member_id":1104127,"lv":60,"ex_flg":1,"rankId":14410},{"id":216142,"member_id":1194125,"lv":60,"ex_flg":1,"rankId":14410},{"id":216143,"member_id":1024113,"lv":60,"ex_flg":1,"rankId":14410},{"id":216144,"member_id":1194100,"lv":60,"ex_flg":1,"rankId":14410},{"id":216145,"member_id":1004141,"lv":60,"ex_flg":1,"rankId":14410},{"id":216146,"member_id":1004116,"lv":60,"ex_flg":1,"rankId":14410},{"id":216147,"member_id":1004127,"lv":60,"ex_flg":1,"rankId":14410},{"id":216148,"member_id":1133128,"lv":60,"ex_flg":1,"rankId":14410},{"id":216149,"member_id":1134110,"lv":60,"ex_flg":1,"rankId":14410},{"id":216150,"member_id":1054113,"lv":60,"ex_flg":1,"rankId":14410}],"party":[{"id":72046,"form_no":1,"main":1024132,"sub1":1143100,"sub2":1024126,"weapon":314406,"acc":224145,"specialskill":102001,"rankId":14410},{"id":72047,"form_no":2,"main":1104100,"sub1":1104116,"sub2":1104127,"weapon":411005,"acc":224166,"specialskill":110002,"rankId":14410},{"id":72048,"form_no":3,"main":1194125,"sub1":1024113,"sub2":1194100,"weapon":124576,"acc":224166,"specialskill":119001,"rankId":14410},{"id":72049,"form_no":4,"main":1004141,"sub1":1004116,"sub2":1004127,"weapon":324106,"acc":224175,"specialskill":100011,"rankId":14410},{"id":72050,"form_no":5,"main":1133128,"sub1":1134110,"sub2":1054113,"weapon":324405,"acc":224165,"specialskill":113002,"rankId":14410}]},{"arena_id":"60","bestscore":2821056,"member":[{"id":345871,"member_id":1114114,"lv":60,"ex_flg":1,"rankId":23059},{"id":345872,"member_id":1114110,"lv":60,"ex_flg":1,"rankId":23059},{"id":345873,"member_id":1113131,"lv":60,"ex_flg":1,"rankId":23059},{"id":345874,"member_id":1174107,"lv":60,"ex_flg":1,"rankId":23059},{"id":345875,"member_id":1174100,"lv":60,"ex_flg":1,"rankId":23059},{"id":345876,"member_id":1124107,"lv":60,"ex_flg":1,"rankId":23059},{"id":345877,"member_id":1143112,"lv":60,"ex_flg":1,"rankId":23059},{"id":345878,"member_id":1143100,"lv":60,"ex_flg":1,"rankId":23059},{"id":345879,"member_id":1143123,"lv":60,"ex_flg":1,"rankId":23059},{"id":345880,"member_id":1074119,"lv":60,"ex_flg":1,"rankId":23059},{"id":345881,"member_id":1073100,"lv":60,"ex_flg":1,"rankId":23059},{"id":345882,"member_id":1074100,"lv":60,"ex_flg":1,"rankId":23059},{"id":345883,"member_id":1004119,"lv":60,"ex_flg":1,"rankId":23059},{"id":345884,"member_id":1004127,"lv":60,"ex_flg":1,"rankId":23059},{"id":345885,"member_id":1003129,"lv":60,"ex_flg":1,"rankId":23059}],"party":[{"id":115291,"form_no":1,"main":1114114,"sub1":1114110,"sub2":1113131,"weapon":411105,"acc":224154,"specialskill":111002,"rankId":23059},{"id":115292,"form_no":2,"main":1174107,"sub1":1174100,"sub2":1124107,"weapon":324305,"acc":224166,"specialskill":117001,"rankId":23059},{"id":115293,"form_no":3,"main":1143112,"sub1":1143100,"sub2":1143123,"weapon":124245,"acc":224135,"specialskill":114002,"rankId":23059},{"id":115294,"form_no":4,"main":1074119,"sub1":1073100,"sub2":1074100,"weapon":324106,"acc":224235,"specialskill":107002,"rankId":23059},{"id":115295,"form_no":5,"main":1004119,"sub1":1004127,"sub2":1003129,"weapon":314106,"acc":224145,"specialskill":100001,"rankId":23059}]}]}