{"user_no":"700976301456","icon":1054135,"highestscore":[{"arena_id":"60","bestscore":2840536,"member":[{"id":360646,"member_id":1113119,"lv":60,"ex_flg":1,"rankId":24044},{"id":360647,"member_id":1113140,"lv":60,"ex_flg":1,"rankId":24044},{"id":360648,"member_id":1014142,"lv":60,"ex_flg":1,"rankId":24044},{"id":360649,"member_id":1024137,"lv":60,"ex_flg":1,"rankId":24044},{"id":360650,"member_id":1143100,"lv":60,"ex_flg":1,"rankId":24044},{"id":360651,"member_id":1183130,"lv":60,"ex_flg":1,"rankId":24044},{"id":360652,"member_id":1174107,"lv":60,"ex_flg":1,"rankId":24044},{"id":360653,"member_id":1174130,"lv":60,"ex_flg":1,"rankId":24044},{"id":360654,"member_id":1174100,"lv":60,"ex_flg":1,"rankId":24044},{"id":360655,"member_id":1074119,"lv":60,"ex_flg":1,"rankId":24044},{"id":360656,"member_id":1074129,"lv":60,"ex_flg":1,"rankId":24044},{"id":360657,"member_id":1074139,"lv":60,"ex_flg":1,"rankId":24044},{"id":360658,"member_id":1004119,"lv":60,"ex_flg":1,"rankId":24044},{"id":360659,"member_id":1004116,"lv":60,"ex_flg":1,"rankId":24044},{"id":360660,"member_id":1004141,"lv":60,"ex_flg":1,"rankId":24044}],"party":[{"id":120216,"form_no":1,"main":1113119,"sub1":1113140,"sub2":1014142,"weapon":314105,"acc":224135,"specialskill":111002,"rankId":24044},{"id":120217,"form_no":2,"main":1024137,"sub1":1143100,"sub2":1183130,"weapon":410205,"acc":224235,"specialskill":102001,"rankId":24044},{"id":120218,"form_no":3,"main":1174107,"sub1":1174130,"sub2":1174100,"weapon":411705,"acc":224135,"specialskill":117001,"rankId":24044},{"id":120219,"form_no":4,"main":1074119,"sub1":1074129,"sub2":1074139,"weapon":410705,"acc":224135,"specialskill":107002,"rankId":24044},{"id":120220,"form_no":5,"main":1004119,"sub1":1004116,"sub2":1004141,"weapon":410005,"acc":224235,"specialskill":100002,"rankId":24044}]}]}