{"user_no":"722752842324","icon":1024118,"highestscore":[{"arena_id":"57","bestscore":3150272,"member":[{"id":7441,"member_id":1024126,"lv":60,"ex_flg":1,"rankId":497},{"id":7442,"member_id":1023107,"lv":60,"ex_flg":1,"rankId":497},{"id":7443,"member_id":1023104,"lv":60,"ex_flg":1,"rankId":497},{"id":7444,"member_id":1134100,"lv":60,"ex_flg":1,"rankId":497},{"id":7445,"member_id":1134123,"lv":60,"ex_flg":1,"rankId":497},{"id":7446,"member_id":1134117,"lv":60,"ex_flg":1,"rankId":497},{"id":7447,"member_id":1094126,"lv":60,"ex_flg":1,"rankId":497},{"id":7448,"member_id":1094114,"lv":60,"ex_flg":1,"rankId":497},{"id":7449,"member_id":1094100,"lv":60,"ex_flg":1,"rankId":497},{"id":7450,"member_id":1004141,"lv":60,"ex_flg":1,"rankId":497},{"id":7451,"member_id":1004127,"lv":60,"ex_flg":1,"rankId":497},{"id":7452,"member_id":1004116,"lv":60,"ex_flg":1,"rankId":497},{"id":7453,"member_id":1044100,"lv":60,"ex_flg":1,"rankId":497},{"id":7454,"member_id":1044125,"lv":60,"ex_flg":1,"rankId":497},{"id":7455,"member_id":1043114,"lv":60,"ex_flg":1,"rankId":497}],"party":[{"id":2481,"form_no":1,"main":1024126,"sub1":1023107,"sub2":1023104,"weapon":410205,"acc":234125,"specialskill":102001,"rankId":497},{"id":2482,"form_no":2,"main":1134100,"sub1":1134123,"sub2":1134117,"weapon":411305,"acc":234126,"specialskill":113002,"rankId":497},{"id":2483,"form_no":3,"main":1094126,"sub1":1094114,"sub2":1094100,"weapon":124555,"acc":234125,"specialskill":109002,"rankId":497},{"id":2484,"form_no":4,"main":1004141,"sub1":1004127,"sub2":1004116,"weapon":324106,"acc":224145,"specialskill":100011,"rankId":497},{"id":2485,"form_no":5,"main":1044100,"sub1":1044125,"sub2":1043114,"weapon":410405,"acc":224145,"specialskill":104001,"rankId":497}]}]}