{"user_no":"838607883514","icon":1013100,"highestscore":[{"arena_id":"60","bestscore":2611952,"member":[{"id":301681,"member_id":1113119,"lv":60,"ex_flg":1,"rankId":20113},{"id":301682,"member_id":1113140,"lv":60,"ex_flg":1,"rankId":20113},{"id":301683,"member_id":1113131,"lv":60,"ex_flg":1,"rankId":20113},{"id":301684,"member_id":1143112,"lv":60,"ex_flg":1,"rankId":20113},{"id":301685,"member_id":1143100,"lv":60,"ex_flg":1,"rankId":20113},{"id":301686,"member_id":1143123,"lv":60,"ex_flg":1,"rankId":20113},{"id":301687,"member_id":1004119,"lv":60,"ex_flg":1,"rankId":20113},{"id":301688,"member_id":1004127,"lv":60,"ex_flg":1,"rankId":20113},{"id":301689,"member_id":1004141,"lv":60,"ex_flg":1,"rankId":20113},{"id":301690,"member_id":1074119,"lv":60,"ex_flg":1,"rankId":20113},{"id":301691,"member_id":1074100,"lv":60,"ex_flg":1,"rankId":20113},{"id":301692,"member_id":1073100,"lv":60,"ex_flg":1,"rankId":20113},{"id":301693,"member_id":1014137,"lv":60,"ex_flg":1,"rankId":20113},{"id":301694,"member_id":1014142,"lv":60,"ex_flg":1,"rankId":20113},{"id":301695,"member_id":1014100,"lv":60,"ex_flg":1,"rankId":20113}],"party":[{"id":100561,"form_no":1,"main":1113119,"sub1":1113140,"sub2":1113131,"weapon":411105,"acc":224133,"specialskill":111002,"rankId":20113},{"id":100562,"form_no":2,"main":1143112,"sub1":1143100,"sub2":1143123,"weapon":334205,"acc":224233,"specialskill":114002,"rankId":20113},{"id":100563,"form_no":3,"main":1004119,"sub1":1004127,"sub2":1004141,"weapon":410005,"acc":223135,"specialskill":100002,"rankId":20113},{"id":100564,"form_no":4,"main":1074119,"sub1":1074100,"sub2":1073100,"weapon":324105,"acc":223134,"specialskill":107002,"rankId":20113},{"id":100565,"form_no":5,"main":1014137,"sub1":1014142,"sub2":1014100,"weapon":410105,"acc":223134,"specialskill":101002,"rankId":20113}]}]}