{"user_no":"925344509948","icon":1024132,"highestscore":[{"arena_id":"57","bestscore":3359456,"member":[{"id":11941,"member_id":1024132,"lv":60,"ex_flg":1,"rankId":797},{"id":11942,"member_id":1024126,"lv":60,"ex_flg":1,"rankId":797},{"id":11943,"member_id":1014142,"lv":60,"ex_flg":1,"rankId":797},{"id":11944,"member_id":1134100,"lv":60,"ex_flg":1,"rankId":797},{"id":11945,"member_id":1134110,"lv":60,"ex_flg":1,"rankId":797},{"id":11946,"member_id":1134123,"lv":60,"ex_flg":1,"rankId":797},{"id":11947,"member_id":1064107,"lv":60,"ex_flg":1,"rankId":797},{"id":11948,"member_id":1064118,"lv":60,"ex_flg":1,"rankId":797},{"id":11949,"member_id":1064100,"lv":60,"ex_flg":1,"rankId":797},{"id":11950,"member_id":1004141,"lv":60,"ex_flg":1,"rankId":797},{"id":11951,"member_id":1004116,"lv":60,"ex_flg":1,"rankId":797},{"id":11952,"member_id":1113140,"lv":60,"ex_flg":1,"rankId":797},{"id":11953,"member_id":1153143,"lv":60,"ex_flg":1,"rankId":797},{"id":11954,"member_id":1154100,"lv":60,"ex_flg":1,"rankId":797},{"id":11955,"member_id":1194117,"lv":60,"ex_flg":1,"rankId":797}],"party":[{"id":3981,"form_no":1,"main":1024132,"sub1":1024126,"sub2":1014142,"weapon":410205,"acc":224125,"specialskill":102001,"rankId":797},{"id":3982,"form_no":2,"main":1134100,"sub1":1134110,"sub2":1134123,"weapon":411305,"acc":224145,"specialskill":113002,"rankId":797},{"id":3983,"form_no":3,"main":1064107,"sub1":1064118,"sub2":1064100,"weapon":324405,"acc":224145,"specialskill":106001,"rankId":797},{"id":3984,"form_no":4,"main":1004141,"sub1":1004116,"sub2":1113140,"weapon":324106,"acc":224145,"specialskill":100001,"rankId":797},{"id":3985,"form_no":5,"main":1153143,"sub1":1154100,"sub2":1194117,"weapon":124556,"acc":224165,"specialskill":115011,"rankId":797}]},{"arena_id":"59","bestscore":2794344,"member":[{"id":200821,"member_id":1024132,"lv":60,"ex_flg":1,"rankId":13389},{"id":200822,"member_id":1014142,"lv":60,"ex_flg":1,"rankId":13389},{"id":200823,"member_id":1024126,"lv":60,"ex_flg":1,"rankId":13389},{"id":200824,"member_id":1104100,"lv":60,"ex_flg":1,"rankId":13389},{"id":200825,"member_id":1104127,"lv":60,"ex_flg":1,"rankId":13389},{"id":200826,"member_id":1103134,"lv":60,"ex_flg":1,"rankId":13389},{"id":200827,"member_id":1194125,"lv":60,"ex_flg":1,"rankId":13389},{"id":200828,"member_id":1194100,"lv":60,"ex_flg":1,"rankId":13389},{"id":200829,"member_id":1054113,"lv":60,"ex_flg":1,"rankId":13389},{"id":200830,"member_id":1004141,"lv":60,"ex_flg":1,"rankId":13389},{"id":200831,"member_id":1004116,"lv":60,"ex_flg":1,"rankId":13389},{"id":200832,"member_id":1004127,"lv":60,"ex_flg":1,"rankId":13389},{"id":200833,"member_id":1133128,"lv":60,"ex_flg":1,"rankId":13389},{"id":200834,"member_id":1134110,"lv":60,"ex_flg":1,"rankId":13389},{"id":200835,"member_id":1024113,"lv":60,"ex_flg":1,"rankId":13389}],"party":[{"id":66941,"form_no":1,"main":1024132,"sub1":1014142,"sub2":1024126,"weapon":410205,"acc":224235,"specialskill":102001,"rankId":13389},{"id":66942,"form_no":2,"main":1104100,"sub1":1104127,"sub2":1103134,"weapon":124476,"acc":224165,"specialskill":110001,"rankId":13389},{"id":66943,"form_no":3,"main":1194125,"sub1":1194100,"sub2":1054113,"weapon":124576,"acc":224165,"specialskill":119001,"rankId":13389},{"id":66944,"form_no":4,"main":1004141,"sub1":1004116,"sub2":1004127,"weapon":324106,"acc":0,"specialskill":100002,"rankId":13389},{"id":66945,"form_no":5,"main":1133128,"sub1":1134110,"sub2":1024113,"weapon":324405,"acc":224155,"specialskill":113011,"rankId":13389}]},{"arena_id":"60","bestscore":2747120,"member":[{"id":316171,"member_id":1113119,"lv":60,"ex_flg":1,"rankId":21079},{"id":316172,"member_id":1113140,"lv":60,"ex_flg":1,"rankId":21079},{"id":316173,"member_id":1114127,"lv":60,"ex_flg":1,"rankId":21079},{"id":316174,"member_id":1024132,"lv":60,"ex_flg":1,"rankId":21079},{"id":316175,"member_id":1024126,"lv":60,"ex_flg":1,"rankId":21079},{"id":316176,"member_id":1014142,"lv":60,"ex_flg":1,"rankId":21079},{"id":316177,"member_id":1004119,"lv":60,"ex_flg":1,"rankId":21079},{"id":316178,"member_id":1004141,"lv":60,"ex_flg":1,"rankId":21079},{"id":316179,"member_id":1004116,"lv":60,"ex_flg":1,"rankId":21079},{"id":316180,"member_id":1143112,"lv":60,"ex_flg":1,"rankId":21079},{"id":316181,"member_id":1144100,"lv":60,"ex_flg":1,"rankId":21079},{"id":316182,"member_id":1143100,"lv":60,"ex_flg":1,"rankId":21079},{"id":316183,"member_id":1074119,"lv":60,"ex_flg":1,"rankId":21079},{"id":316184,"member_id":1073100,"lv":60,"ex_flg":1,"rankId":21079},{"id":316185,"member_id":1074100,"lv":60,"ex_flg":1,"rankId":21079}],"party":[{"id":105391,"form_no":1,"main":1113119,"sub1":1113140,"sub2":1114127,"weapon":411105,"acc":224175,"specialskill":111002,"rankId":21079},{"id":105392,"form_no":2,"main":1024132,"sub1":1024126,"sub2":1014142,"weapon":410205,"acc":344006,"specialskill":102001,"rankId":21079},{"id":105393,"form_no":3,"main":1004119,"sub1":1004141,"sub2":1004116,"weapon":324106,"acc":224135,"specialskill":100002,"rankId":21079},{"id":105394,"form_no":4,"main":1143112,"sub1":1144100,"sub2":1143100,"weapon":334205,"acc":224135,"specialskill":114002,"rankId":21079},{"id":105395,"form_no":5,"main":1074119,"sub1":1073100,"sub2":1074100,"weapon":410705,"acc":224235,"specialskill":107011,"rankId":21079}]}]}