{"user_no":"956361889161","icon":1123120,"highestscore":[{"arena_id":"57","bestscore":3896240,"member":[{"id":29791,"member_id":1024132,"lv":60,"ex_flg":1,"rankId":1987},{"id":29792,"member_id":1024126,"lv":60,"ex_flg":1,"rankId":1987},{"id":29793,"member_id":1143100,"lv":60,"ex_flg":1,"rankId":1987},{"id":29794,"member_id":1134100,"lv":60,"ex_flg":1,"rankId":1987},{"id":29795,"member_id":1134110,"lv":60,"ex_flg":1,"rankId":1987},{"id":29796,"member_id":1134117,"lv":60,"ex_flg":1,"rankId":1987},{"id":29797,"member_id":1153143,"lv":60,"ex_flg":1,"rankId":1987},{"id":29798,"member_id":1154100,"lv":60,"ex_flg":1,"rankId":1987},{"id":29799,"member_id":1154117,"lv":60,"ex_flg":1,"rankId":1987},{"id":29800,"member_id":1004141,"lv":60,"ex_flg":1,"rankId":1987},{"id":29801,"member_id":1014142,"lv":60,"ex_flg":1,"rankId":1987},{"id":29802,"member_id":1004116,"lv":60,"ex_flg":1,"rankId":1987},{"id":29803,"member_id":1044100,"lv":60,"ex_flg":1,"rankId":1987},{"id":29804,"member_id":1044125,"lv":60,"ex_flg":1,"rankId":1987},{"id":29805,"member_id":1044110,"lv":60,"ex_flg":1,"rankId":1987}],"party":[{"id":9931,"form_no":1,"main":1024132,"sub1":1024126,"sub2":1143100,"weapon":410205,"acc":224156,"specialskill":102001,"rankId":1987},{"id":9932,"form_no":2,"main":1134100,"sub1":1134110,"sub2":1134117,"weapon":411305,"acc":224145,"specialskill":113002,"rankId":1987},{"id":9933,"form_no":3,"main":1153143,"sub1":1154100,"sub2":1154117,"weapon":124556,"acc":224145,"specialskill":115011,"rankId":1987},{"id":9934,"form_no":4,"main":1004141,"sub1":1014142,"sub2":1004116,"weapon":324106,"acc":224145,"specialskill":100002,"rankId":1987},{"id":9935,"form_no":5,"main":1044100,"sub1":1044125,"sub2":1044110,"weapon":324306,"acc":223146,"specialskill":104001,"rankId":1987}]},{"arena_id":"58","bestscore":3772224,"member":[{"id":192931,"member_id":1024132,"lv":60,"ex_flg":1,"rankId":12863},{"id":192932,"member_id":1024126,"lv":60,"ex_flg":1,"rankId":12863},{"id":192933,"member_id":1024141,"lv":60,"ex_flg":1,"rankId":12863},{"id":192934,"member_id":1053127,"lv":60,"ex_flg":1,"rankId":12863},{"id":192935,"member_id":1053139,"lv":60,"ex_flg":1,"rankId":12863},{"id":192936,"member_id":1054100,"lv":60,"ex_flg":1,"rankId":12863},{"id":192937,"member_id":1134117,"lv":60,"ex_flg":1,"rankId":12863},{"id":192938,"member_id":1134110,"lv":60,"ex_flg":1,"rankId":12863},{"id":192939,"member_id":1014132,"lv":60,"ex_flg":1,"rankId":12863},{"id":192940,"member_id":1004141,"lv":60,"ex_flg":1,"rankId":12863},{"id":192941,"member_id":1004116,"lv":60,"ex_flg":1,"rankId":12863},{"id":192942,"member_id":1014142,"lv":60,"ex_flg":1,"rankId":12863},{"id":192943,"member_id":1064100,"lv":60,"ex_flg":1,"rankId":12863},{"id":192944,"member_id":1064118,"lv":60,"ex_flg":1,"rankId":12863},{"id":192945,"member_id":1063116,"lv":60,"ex_flg":1,"rankId":12863}],"party":[{"id":64311,"form_no":1,"main":1024132,"sub1":1024126,"sub2":1024141,"weapon":410205,"acc":223175,"specialskill":102001,"rankId":12863},{"id":64312,"form_no":2,"main":1053127,"sub1":1053139,"sub2":1054100,"weapon":410505,"acc":223176,"specialskill":105002,"rankId":12863},{"id":64313,"form_no":3,"main":1134117,"sub1":1134110,"sub2":1014132,"weapon":324406,"acc":224175,"specialskill":113002,"rankId":12863},{"id":64314,"form_no":4,"main":1004141,"sub1":1004116,"sub2":1014142,"weapon":324106,"acc":0,"specialskill":100002,"rankId":12863},{"id":64315,"form_no":5,"main":1064100,"sub1":1064118,"sub2":1063116,"weapon":410605,"acc":223176,"specialskill":106002,"rankId":12863}]},{"arena_id":"59","bestscore":3673880,"member":[{"id":239731,"member_id":1024132,"lv":60,"ex_flg":1,"rankId":15983},{"id":239732,"member_id":1024100,"lv":60,"ex_flg":1,"rankId":15983},{"id":239733,"member_id":1024141,"lv":60,"ex_flg":1,"rankId":15983},{"id":239734,"member_id":1194125,"lv":60,"ex_flg":1,"rankId":15983},{"id":239735,"member_id":1194100,"lv":60,"ex_flg":1,"rankId":15983},{"id":239736,"member_id":1024113,"lv":60,"ex_flg":1,"rankId":15983},{"id":239737,"member_id":1104100,"lv":60,"ex_flg":1,"rankId":15983},{"id":239738,"member_id":1104110,"lv":60,"ex_flg":1,"rankId":15983},{"id":239739,"member_id":1104116,"lv":60,"ex_flg":1,"rankId":15983},{"id":239740,"member_id":1004141,"lv":60,"ex_flg":1,"rankId":15983},{"id":239741,"member_id":1014142,"lv":60,"ex_flg":1,"rankId":15983},{"id":239742,"member_id":1004116,"lv":60,"ex_flg":1,"rankId":15983},{"id":239743,"member_id":1133128,"lv":60,"ex_flg":1,"rankId":15983},{"id":239744,"member_id":1134110,"lv":60,"ex_flg":1,"rankId":15983},{"id":239745,"member_id":1024126,"lv":60,"ex_flg":1,"rankId":15983}],"party":[{"id":79911,"form_no":1,"main":1024132,"sub1":1024100,"sub2":1024141,"weapon":410205,"acc":344006,"specialskill":102001,"rankId":15983},{"id":79912,"form_no":2,"main":1194125,"sub1":1194100,"sub2":1024113,"weapon":124576,"acc":224166,"specialskill":119001,"rankId":15983},{"id":79913,"form_no":3,"main":1104100,"sub1":1104110,"sub2":1104116,"weapon":411005,"acc":224166,"specialskill":110002,"rankId":15983},{"id":79914,"form_no":4,"main":1004141,"sub1":1014142,"sub2":1004116,"weapon":324106,"acc":233140,"specialskill":100011,"rankId":15983},{"id":79915,"form_no":5,"main":1133128,"sub1":1134110,"sub2":1024126,"weapon":324406,"acc":224165,"specialskill":113011,"rankId":15983}]},{"arena_id":"60","bestscore":3614528,"member":[{"id":344776,"member_id":1113119,"lv":60,"ex_flg":1,"rankId":22986},{"id":344777,"member_id":1113140,"lv":60,"ex_flg":1,"rankId":22986},{"id":344778,"member_id":1014142,"lv":60,"ex_flg":1,"rankId":22986},{"id":344779,"member_id":1024137,"lv":60,"ex_flg":1,"rankId":22986},{"id":344780,"member_id":1143100,"lv":60,"ex_flg":1,"rankId":22986},{"id":344781,"member_id":1183130,"lv":60,"ex_flg":1,"rankId":22986},{"id":344782,"member_id":1174107,"lv":60,"ex_flg":1,"rankId":22986},{"id":344783,"member_id":1174130,"lv":60,"ex_flg":1,"rankId":22986},{"id":344784,"member_id":1034142,"lv":60,"ex_flg":1,"rankId":22986},{"id":344785,"member_id":1074119,"lv":60,"ex_flg":1,"rankId":22986},{"id":344786,"member_id":1074129,"lv":60,"ex_flg":1,"rankId":22986},{"id":344787,"member_id":1074139,"lv":60,"ex_flg":1,"rankId":22986},{"id":344788,"member_id":1004119,"lv":60,"ex_flg":1,"rankId":22986},{"id":344789,"member_id":1004116,"lv":60,"ex_flg":1,"rankId":22986},{"id":344790,"member_id":1004141,"lv":60,"ex_flg":1,"rankId":22986}],"party":[{"id":114926,"form_no":1,"main":1113119,"sub1":1113140,"sub2":1014142,"weapon":411105,"acc":224135,"specialskill":111002,"rankId":22986},{"id":114927,"form_no":2,"main":1024137,"sub1":1143100,"sub2":1183130,"weapon":410205,"acc":224235,"specialskill":102001,"rankId":22986},{"id":114928,"form_no":3,"main":1174107,"sub1":1174130,"sub2":1034142,"weapon":324306,"acc":224136,"specialskill":117001,"rankId":22986},{"id":114929,"form_no":4,"main":1074119,"sub1":1074129,"sub2":1074139,"weapon":324106,"acc":224135,"specialskill":107002,"rankId":22986},{"id":114930,"form_no":5,"main":1004119,"sub1":1004116,"sub2":1004141,"weapon":410005,"acc":223136,"specialskill":100011,"rankId":22986}]}]}